openstarlab_rlearn-0.1.30.dist-info/licenses/LICENSE
rlearn/__init__.py
rlearn/sports/__init__.py
rlearn/sports/main_class.py
rlearn/sports/pytest_main_class.py
rlearn/sports/soccer/__init__.py
rlearn/sports/soccer/constant.py
rlearn/sports/soccer/dataclass.py
rlearn/sports/soccer/env.py
rlearn/sports/soccer/source.py
rlearn/sports/soccer/application/q_values_csv.py
rlearn/sports/soccer/application/q_values_movie.py
rlearn/sports/soccer/application/q_values_movie_new.py
rlearn/sports/soccer/application/q_values_movie_refactored.py
rlearn/sports/soccer/class_weight/__init__.py
rlearn/sports/soccer/class_weight/class_weight.py
rlearn/sports/soccer/main_class_soccer/main.py
rlearn/sports/soccer/models/__init__.py
rlearn/sports/soccer/models/dqn.py
rlearn/sports/soccer/models/observation_action_predictor.py
rlearn/sports/soccer/models/observation_action_predictor_with_action_loss.py
rlearn/sports/soccer/models/q_model_base.py
rlearn/sports/soccer/models/sarsa.py
rlearn/sports/soccer/modules/__init__.py
rlearn/sports/soccer/modules/optimizer.py
rlearn/sports/soccer/modules/datamodule/__init__.py
rlearn/sports/soccer/modules/datamodule/datamodule.py
rlearn/sports/soccer/modules/datamodule/jleague_observation_action.py
rlearn/sports/soccer/modules/datamodule/jleague_observation_action_with_eos.py
rlearn/sports/soccer/modules/datamodule/jleague_only_attackers.py
rlearn/sports/soccer/modules/seq2seq_encoder/__init__.py
rlearn/sports/soccer/modules/seq2seq_encoder/pass_through_encoder.py
rlearn/sports/soccer/modules/seq2seq_encoder/pytoch_transformer_encoder.py
rlearn/sports/soccer/modules/seq2seq_encoder/pytorch_seq2seq_wrapper.py
rlearn/sports/soccer/modules/seq2seq_encoder/seq2seq_encoder.py
rlearn/sports/soccer/modules/sequence_decoder/__init__.py
rlearn/sports/soccer/modules/sequence_decoder/huggingface_gpt2_decoder.py
rlearn/sports/soccer/modules/sequence_decoder/sequence_decoder.py
rlearn/sports/soccer/modules/state_action_tokenizer/___init__.py
rlearn/sports/soccer/modules/state_action_tokenizer/preprocess_frames.py
openstarlab_rlearn-0.1.30.dist-info/METADATA
openstarlab_rlearn-0.1.30.dist-info/WHEEL
openstarlab_rlearn-0.1.30.dist-info/top_level.txt
openstarlab_rlearn-0.1.30.dist-info/RECORD
