Metadata-Version: 2.4
Name: openstarlab_rlearn
Version: 0.1.30
Summary: openstarlab rlearn modeliing package
Author-email: Kenjiro Ide <ide.kenjirog@g.sp.m.is.nagoya-u.ac.jp>
License: Apache License 2.0
Project-URL: Homepage, https://github.com/open-starlab/RLearn
Classifier: Programming Language :: Python :: 3
Classifier: License :: OSI Approved :: Apache Software License
Classifier: Operating System :: OS Independent
Requires-Python: >=3.10
License-File: LICENSE
Requires-Dist: pandas>=1.3.0
Requires-Dist: numpy>=1.21.0
Requires-Dist: ai2-tango==1.3.2
Requires-Dist: bidict>=0.22.1
Requires-Dist: chardet==5.2.0
Requires-Dist: datasets>=3.0.1
Requires-Dist: fire==0.5.0
Requires-Dist: japanize-matplotlib==1.1.3
Requires-Dist: jsonlines>=3.1.0
Requires-Dist: lightning-lite>=1.8.6
Requires-Dist: matplotlib==3.9.0
Requires-Dist: matplotsoccer>=0.0.8
Requires-Dist: mlflow>=2.16.0
Requires-Dist: tensorboard>=2.18.0
Requires-Dist: tensorboardX>=2.6.0.0
Requires-Dist: opencv-python>=4.10.0
Requires-Dist: pyarrow<20.0.0,>=4.0.0
Requires-Dist: pydantic>=2.9.0
Requires-Dist: pytorch-lightning>=2.4.0
Requires-Dist: scikit-learn>=1.5.0
Requires-Dist: scipy==1.10.1
Requires-Dist: torchmetrics==1.4.0
Requires-Dist: tqdm
Requires-Dist: cloudpickle>=3.0.0
Requires-Dist: importlib-metadata<=8.5,>=6.0
Requires-Dist: packaging>=23.0
Dynamic: license-file
